napari_event_monitor/__init__.py
napari_event_monitor/monitor.py
napari_event_monitor/napari.yaml
napari_event_monitor-0.1.3.dist-info/licenses/LICENSE
napari_event_monitor-0.1.3.dist-info/METADATA
napari_event_monitor-0.1.3.dist-info/WHEEL
napari_event_monitor-0.1.3.dist-info/entry_points.txt
napari_event_monitor-0.1.3.dist-info/top_level.txt
napari_event_monitor-0.1.3.dist-info/RECORD
