Metadata-Version: 2.4
Name: napari-event-monitor
Version: 0.1.3
Summary: Dynamic event monitoring and diagnostics in napari
Author-email: Ian Coccimiglio <icoccimi@gmail.com>
License-Expression: MIT
Project-URL: Homepage, https://github.com/ian-coccimiglio/napari-event-monitor
Project-URL: Issues, https://github.com/ian-coccimiglio/napari-event-monitor/issues/
Classifier: Programming Language :: Python :: 3
Classifier: Operating System :: OS Independent
Classifier: Framework :: napari
Requires-Python: >3.10
License-File: LICENSE
Dynamic: license-file
